socklint/__init__.py
socklint-0.0.1.dist-info/LICENSE.md
socklint-0.0.1.dist-info/METADATA
socklint-0.0.1.dist-info/WHEEL
socklint-0.0.1.dist-info/top_level.txt
socklint-0.0.1.dist-info/RECORD
