Metadata-Version: 2.1
Name: socklint
Version: 0.0.1
Summary: API objects used by Sock Puppet
Home-page: https://github.com/JesseTG/socklint
Author: Jesse Talavera-Greenberg
Author-email: jessetalavera@aol.com
License: BSD
Download-URL: https://github.com/JesseTG/socklint/tarball/0.0.1
Platform: UNKNOWN
Classifier: Development Status :: 3 - Alpha
Classifier: Intended Audience :: Developers
Classifier: Programming Language :: Python :: 3
